dsf/__init__.py
dsf/random_UA.py
dsf-3.0.1.dist-info/LICENSE
dsf-3.0.1.dist-info/METADATA
dsf-3.0.1.dist-info/WHEEL
dsf-3.0.1.dist-info/top_level.txt
dsf-3.0.1.dist-info/zip-safe
dsf-3.0.1.dist-info/RECORD
