Metadata-Version: 2.1
Name: dsf
Version: 3.0.1
Summary: this is a test package for packing python liberaries tutorial.  dsfdsf
Home-page: http://blog.useasp.net/
Author: dsf
Author-email: 2226893225@qq.com
License: MIT
Keywords: test python package
Platform: UNKNOWN
Classifier: License :: OSI Approved :: MIT License
Classifier: Programming Language :: Python
Classifier: Intended Audience :: Developers
Classifier: Operating System :: OS Independent
